{"marca":"jac","marcaNombre":"JAC","modelo":"X200","version":"X200 E5","motor":null,"segmento":null,"categoria":null,"vigencia":"Activo","tarifaMO":44550,"anios":null,"planes":[{"anio":null,"intervalos":[{"n":1,"km":10000,"etiqueta":"10.000 km","meses":6,"horas":1.8,"manoObra":80190,"items":[{"tipo":"repuesto","nombre":"Filtro de Aceite","codigo":"1010320FD060","cantidad":1.0,"precioUnitario":13752,"subtotal":13752},{"tipo":"material","nombre":"Materiales","codigo":"Mat-001","cantidad":1.0,"precioUnitario":17255,"subtotal":17255},{"tipo":"lubricante","nombre":"Aceite de Motor Mobil Delvac 1300 Super 15W 40 (15W/40  CJ-4)","codigo":"106324","cantidad":6.3,"precioUnitario":9124,"subtotal":57479}],"totalConIva":169000,"totalNeto":142017,"conDescuento":null,"gratis":false,"operaciones":[{"nombre":"Aceite de Motor/ fIltro","accion":"C"},{"nombre":"Aceite de Transmision MT","accion":"I"},{"nombre":"Liquido de Frenos","accion":"I"},{"nombre":"Refrigerante","accion":"I"},{"nombre":"Liquido Limpia Parabrisas","accion":"I"},{"nombre":"Filtro de Aire","accion":"I"},{"nombre":"Filtro de Polen","accion":"I"},{"nombre":"Filtro de Combustible","accion":"I"},{"nombre":"PRE -Filtro de Combustible","accion":"I"},{"nombre":"Golilla tapon de carter","accion":"C"},{"nombre":"correa de accesorios","accion":"I"},{"nombre":"Aceite de direccion","accion":"I"},{"nombre":"Revision sistema de direccion","accion":"I"},{"nombre":"Reapriete tren tras/delan","accion":"I"},{"nombre":"Servicios de frenos/ freno de mano","accion":"I"},{"nombre":"Diferencial trasero","accion":"I"},{"nombre":"Diferencial delantero (4wd / T6,T8,T9)","accion":"I"},{"nombre":"Caja de transferencia  (4wd / T6,T8,T9)","accion":"I"},{"nombre":"Revisar fugas y nivel de adblue.","accion":"I"},{"nombre":"Lectura momoria de averías","accion":"I"}],"totalCalculado":168676},{"n":2,"km":20000,"etiqueta":"20.000 km","meses":12,"horas":2.5,"manoObra":111375,"items":[{"tipo":"repuesto","nombre":"Filtro de Aceite","codigo":"1010320FD060","cantidad":1.0,"precioUnitario":13752,"subtotal":13752},{"tipo":"repuesto","nombre":"Filtro de Aire","codigo":"1109140W5000","cantidad":1.0,"precioUnitario":25014,"subtotal":25014},{"tipo":"repuesto","nombre":"Filtro  de Combustible","codigo":"1105012W5030","cantidad":1.0,"precioUnitario":59726,"subtotal":59726},{"tipo":"repuesto","nombre":"PRE-Filtro de Combustible","codigo":"1105022W5032","cantidad":1.0,"precioUnitario":59726,"subtotal":59726},{"tipo":"material","nombre":"Materiales","codigo":"Mat-001","cantidad":1.0,"precioUnitario":17255,"subtotal":17255},{"tipo":"lubricante","nombre":"Aceite de Motor Mobil Delvac 1300 Super 15W 40 (15W/40  CJ-4)","codigo":"106324","cantidad":6.3,"precioUnitario":9124,"subtotal":57479}],"totalConIva":344000,"totalNeto":289076,"conDescuento":null,"gratis":false,"operaciones":[{"nombre":"Aceite de Motor/ fIltro","accion":"C"},{"nombre":"Aceite de Transmision MT","accion":"I"},{"nombre":"Liquido de Frenos","accion":"I"},{"nombre":"Refrigerante","accion":"I"},{"nombre":"Liquido Limpia Parabrisas","accion":"I"},{"nombre":"Filtro de Aire","accion":"C"},{"nombre":"Filtro de Polen","accion":"I"},{"nombre":"Filtro de Combustible","accion":"C"},{"nombre":"PRE -Filtro de Combustible","accion":"C"},{"nombre":"Golilla tapon de carter","accion":"C"},{"nombre":"correa de accesorios","accion":"I"},{"nombre":"Aceite de direccion","accion":"I"},{"nombre":"Revision sistema de direccion","accion":"I"},{"nombre":"Reapriete tren tras/delan","accion":"I"},{"nombre":"Servicios de frenos/ freno de mano","accion":"I"},{"nombre":"Diferencial trasero","accion":"I"},{"nombre":"Diferencial delantero (4wd / T6,T8,T9)","accion":"I"},{"nombre":"Caja de transferencia  (4wd / T6,T8,T9)","accion":"I"},{"nombre":"Revisar fugas y nivel de adblue.","accion":"I"},{"nombre":"Lectura momoria de averías","accion":"I"}],"totalCalculado":344327},{"n":3,"km":30000,"etiqueta":"30.000 km","meses":18,"horas":2.0,"manoObra":89100,"items":[{"tipo":"repuesto","nombre":"Filtro de Aceite","codigo":"1010320FD060","cantidad":1.0,"precioUnitario":13752,"subtotal":13752},{"tipo":"repuesto","nombre":"Filtro de Polén","codigo":"8126108W5000","cantidad":1.0,"precioUnitario":5469,"subtotal":5469},{"tipo":"material","nombre":"Materiales","codigo":"Mat-001","cantidad":1.0,"precioUnitario":17255,"subtotal":17255},{"tipo":"lubricante","nombre":"Aceite de Motor Mobil Delvac 1300 Super 15W 40 (15W/40  CJ-4)","codigo":"106324","cantidad":6.3,"precioUnitario":9124,"subtotal":57479},{"tipo":"lubricante","nombre":"Aceite diferencial Mobilube Hd Plus 80w-90 (Gl-5)","codigo":"100214","cantidad":2.4,"precioUnitario":7186,"subtotal":17247}],"totalConIva":200000,"totalNeto":168067,"conDescuento":null,"gratis":false,"operaciones":[{"nombre":"Aceite de Motor/ fIltro","accion":"C"},{"nombre":"Aceite de Transmision MT","accion":"I"},{"nombre":"Liquido de Frenos","accion":"I"},{"nombre":"Refrigerante","accion":"I"},{"nombre":"Liquido Limpia Parabrisas","accion":"I"},{"nombre":"Filtro de Aire","accion":"I"},{"nombre":"Filtro de Polen","accion":"I"},{"nombre":"Filtro de Combustible","accion":"I"},{"nombre":"PRE -Filtro de Combustible","accion":"I"},{"nombre":"Golilla tapon de carter","accion":"C"},{"nombre":"correa de accesorios","accion":"I"},{"nombre":"Aceite de direccion","accion":"I"},{"nombre":"Revision sistema de direccion","accion":"I"},{"nombre":"Reapriete tren tras/delan","accion":"I"},{"nombre":"Servicios de frenos/ freno de mano","accion":"I"},{"nombre":"Diferencial trasero","accion":"C"},{"nombre":"Diferencial delantero (4wd / T6,T8,T9)","accion":"C"},{"nombre":"Caja de transferencia  (4wd / T6,T8,T9)","accion":"C"},{"nombre":"Revisar fugas y nivel de adblue.","accion":"I"},{"nombre":"Lectura momoria de averías","accion":"I"}],"totalCalculado":200303},{"n":4,"km":40000,"etiqueta":"40.000 km","meses":24,"horas":3.8,"manoObra":169290,"items":[{"tipo":"repuesto","nombre":"Filtro de Aceite","codigo":"1010320FD060","cantidad":1.0,"precioUnitario":13752,"subtotal":13752},{"tipo":"repuesto","nombre":"Filtro de Aire","codigo":"1109140W5000","cantidad":1.0,"precioUnitario":25014,"subtotal":25014},{"tipo":"repuesto","nombre":"Filtro  de Combustible","codigo":"1105012W5030","cantidad":1.0,"precioUnitario":59726,"subtotal":59726},{"tipo":"repuesto","nombre":"PRE-Filtro de Combustible","codigo":"1105022W5032","cantidad":1.0,"precioUnitario":59726,"subtotal":59726},{"tipo":"material","nombre":"Materiales","codigo":"Mat-001","cantidad":1.0,"precioUnitario":17255,"subtotal":17255},{"tipo":"lubricante","nombre":"Aceite de Motor Mobil Delvac 1300 Super 15W 40 (15W/40  CJ-4)","codigo":"106324","cantidad":6.3,"precioUnitario":9124,"subtotal":57479},{"tipo":"lubricante","nombre":"Líquido de Frenos y Embrague DOT-4","codigo":"100051","cantidad":2.0,"precioUnitario":6099,"subtotal":12198}],"totalConIva":414000,"totalNeto":347899,"conDescuento":null,"gratis":false,"operaciones":[{"nombre":"Aceite de Motor/ fIltro","accion":"C"},{"nombre":"Aceite de Transmision MT","accion":"I"},{"nombre":"Liquido de Frenos","accion":"C"},{"nombre":"Refrigerante","accion":"I"},{"nombre":"Liquido Limpia Parabrisas","accion":"I"},{"nombre":"Filtro de Aire","accion":"C"},{"nombre":"Filtro de Polen","accion":"I"},{"nombre":"Filtro de Combustible","accion":"C"},{"nombre":"PRE -Filtro de Combustible","accion":"C"},{"nombre":"Golilla tapon de carter","accion":"C"},{"nombre":"correa de accesorios","accion":"I"},{"nombre":"Aceite de direccion","accion":"I"},{"nombre":"Revision sistema de direccion","accion":"I"},{"nombre":"Reapriete tren tras/delan","accion":"I"},{"nombre":"Servicios de frenos/ freno de mano","accion":"I"},{"nombre":"Diferencial trasero","accion":"I"},{"nombre":"Diferencial delantero (4wd / T6,T8,T9)","accion":"I"},{"nombre":"Caja de transferencia  (4wd / T6,T8,T9)","accion":"I"},{"nombre":"Revisar fugas y nivel de adblue.","accion":"I"},{"nombre":"Lectura momoria de averías","accion":"I"}],"totalCalculado":414440},{"n":5,"km":50000,"etiqueta":"50.000 km","meses":30,"horas":2.2,"manoObra":98010,"items":[{"tipo":"repuesto","nombre":"Filtro de Aceite","codigo":"1010320FD060","cantidad":1.0,"precioUnitario":13752,"subtotal":13752},{"tipo":"material","nombre":"Materiales","codigo":"Mat-001","cantidad":1.0,"precioUnitario":17255,"subtotal":17255},{"tipo":"lubricante","nombre":"Aceite de Motor Mobil Delvac 1300 Super 15W 40 (15W/40  CJ-4)","codigo":"106324","cantidad":6.3,"precioUnitario":9124,"subtotal":57479},{"tipo":"lubricante","nombre":"Aceite de Dirección","codigo":"100280","cantidad":1.7,"precioUnitario":8180,"subtotal":13906},{"tipo":"lubricante","nombre":"Anticongelante Mobil Super ELC 50%","codigo":"105892","cantidad":11.5,"precioUnitario":7765,"subtotal":89295}],"totalConIva":290000,"totalNeto":243697,"conDescuento":null,"gratis":false,"operaciones":[{"nombre":"Aceite de Motor/ fIltro","accion":"C"},{"nombre":"Aceite de Transmision MT","accion":"I"},{"nombre":"Liquido de Frenos","accion":"I"},{"nombre":"Refrigerante","accion":"C"},{"nombre":"Liquido Limpia Parabrisas","accion":"I"},{"nombre":"Filtro de Aire","accion":"I"},{"nombre":"Filtro de Polen","accion":"I"},{"nombre":"Filtro de Combustible","accion":"I"},{"nombre":"PRE -Filtro de Combustible","accion":"I"},{"nombre":"Golilla tapon de carter","accion":"C"},{"nombre":"correa de accesorios","accion":"I"},{"nombre":"Aceite de direccion","accion":"C"},{"nombre":"Revision sistema de direccion","accion":"I"},{"nombre":"Reapriete tren tras/delan","accion":"I"},{"nombre":"Servicios de frenos/ freno de mano","accion":"I"},{"nombre":"Diferencial trasero","accion":"I"},{"nombre":"Diferencial delantero (4wd / T6,T8,T9)","accion":"I"},{"nombre":"Caja de transferencia  (4wd / T6,T8,T9)","accion":"I"},{"nombre":"Revisar fugas y nivel de adblue.","accion":"I"},{"nombre":"Lectura momoria de averías","accion":"I"}],"totalCalculado":289697},{"n":6,"km":60000,"etiqueta":"60.000 km","meses":36,"horas":4.0,"manoObra":178200,"items":[{"tipo":"repuesto","nombre":"Filtro de Aceite","codigo":"1010320FD060","cantidad":1.0,"precioUnitario":13752,"subtotal":13752},{"tipo":"repuesto","nombre":"Filtro de Aire","codigo":"1109140W5000","cantidad":1.0,"precioUnitario":25014,"subtotal":25014},{"tipo":"repuesto","nombre":"Filtro de Polén","codigo":"8126108W5000","cantidad":1.0,"precioUnitario":5469,"subtotal":5469},{"tipo":"repuesto","nombre":"Filtro  de Combustible","codigo":"1105012W5030","cantidad":1.0,"precioUnitario":59726,"subtotal":59726},{"tipo":"repuesto","nombre":"PRE-Filtro de Combustible","codigo":"1105022W5032","cantidad":1.0,"precioUnitario":59726,"subtotal":59726},{"tipo":"material","nombre":"Materiales","codigo":"Mat-001","cantidad":1.0,"precioUnitario":17255,"subtotal":17255},{"tipo":"lubricante","nombre":"Aceite de Motor Mobil Delvac 1300 Super 15W 40 (15W/40  CJ-4)","codigo":"106324","cantidad":6.3,"precioUnitario":9124,"subtotal":57479},{"tipo":"lubricante","nombre":"Aceite de transmision Mobilube 1 Shc 75w-90 GL-4","codigo":"100219","cantidad":2.4,"precioUnitario":31458,"subtotal":75498},{"tipo":"lubricante","nombre":"Aceite diferencial Mobilube Hd Plus 80w-90 (Gl-5)","codigo":"100214","cantidad":2.4,"precioUnitario":7186,"subtotal":17247}],"totalConIva":509000,"totalNeto":427731,"conDescuento":null,"gratis":false,"operaciones":[{"nombre":"Aceite de Motor/ fIltro","accion":"C"},{"nombre":"Aceite de Transmision MT","accion":"C"},{"nombre":"Liquido de Frenos","accion":"I"},{"nombre":"Refrigerante","accion":"I"},{"nombre":"Liquido Limpia Parabrisas","accion":"I"},{"nombre":"Filtro de Aire","accion":"C"},{"nombre":"Filtro de Polen","accion":"I"},{"nombre":"Filtro de Combustible","accion":"C"},{"nombre":"PRE -Filtro de Combustible","accion":"C"},{"nombre":"Golilla tapon de carter","accion":"C"},{"nombre":"correa de accesorios","accion":"I"},{"nombre":"correo de distribucion (T6 GASOLINA )","accion":"C"},{"nombre":"Aceite de direccion","accion":"I"},{"nombre":"Revision sistema de direccion","accion":"I"},{"nombre":"Reapriete tren tras/delan","accion":"I"},{"nombre":"Servicios de frenos/ freno de mano","accion":"I"},{"nombre":"Diferencial trasero","accion":"C"},{"nombre":"Diferencial delantero (4wd / T6,T8,T9)","accion":"C"},{"nombre":"Caja de transferencia  (4wd / T6,T8,T9)","accion":"C"},{"nombre":"Revisar fugas y nivel de adblue.","accion":"I"},{"nombre":"Lectura momoria de averías","accion":"I"}],"totalCalculado":509367},{"n":7,"km":70000,"etiqueta":"70.000 km","meses":42,"horas":2.0,"manoObra":89100,"items":[{"tipo":"repuesto","nombre":"Filtro de Aceite","codigo":"1010320FD060","cantidad":1.0,"precioUnitario":13752,"subtotal":13752},{"tipo":"material","nombre":"Materiales","codigo":"Mat-001","cantidad":1.0,"precioUnitario":17255,"subtotal":17255},{"tipo":"lubricante","nombre":"Aceite de Motor Mobil Delvac 1300 Super 15W 40 (15W/40  CJ-4)","codigo":"106324","cantidad":6.3,"precioUnitario":9124,"subtotal":57479},{"tipo":"lubricante","nombre":"Líquido de Frenos y Embrague DOT-4","codigo":"100051","cantidad":2.0,"precioUnitario":6099,"subtotal":12198}],"totalConIva":190000,"totalNeto":159664,"conDescuento":null,"gratis":false,"operaciones":[{"nombre":"Aceite de Motor/ fIltro","accion":"C"},{"nombre":"Aceite de Transmision MT","accion":"I"},{"nombre":"Liquido de Frenos","accion":"I"},{"nombre":"Refrigerante","accion":"I"},{"nombre":"Liquido Limpia Parabrisas","accion":"I"},{"nombre":"Filtro de Aire","accion":"I"},{"nombre":"Filtro de Polen","accion":"I"},{"nombre":"Filtro de Combustible","accion":"I"},{"nombre":"PRE -Filtro de Combustible","accion":"I"},{"nombre":"Golilla tapon de carter","accion":"C"},{"nombre":"correa de accesorios","accion":"I"},{"nombre":"Aceite de direccion","accion":"I"},{"nombre":"Revision sistema de direccion","accion":"I"},{"nombre":"Reapriete tren tras/delan","accion":"I"},{"nombre":"Servicios de frenos/ freno de mano","accion":"I"},{"nombre":"Diferencial trasero","accion":"I"},{"nombre":"Diferencial delantero (4wd / T6,T8,T9)","accion":"I"},{"nombre":"Caja de transferencia  (4wd / T6,T8,T9)","accion":"I"},{"nombre":"Revisar fugas y nivel de adblue.","accion":"I"},{"nombre":"Lectura momoria de averías","accion":"I"}],"totalCalculado":189784},{"n":8,"km":80000,"etiqueta":"80.000 km","meses":48,"horas":3.5,"manoObra":155925,"items":[{"tipo":"repuesto","nombre":"Filtro de Aceite","codigo":"1010320FD060","cantidad":1.0,"precioUnitario":13752,"subtotal":13752},{"tipo":"repuesto","nombre":"Filtro de Aire","codigo":"1109140W5000","cantidad":1.0,"precioUnitario":25014,"subtotal":25014},{"tipo":"repuesto","nombre":"Filtro  de Combustible","codigo":"1105012W5030","cantidad":1.0,"precioUnitario":59726,"subtotal":59726},{"tipo":"repuesto","nombre":"PRE-Filtro de Combustible","codigo":"1105022W5032","cantidad":1.0,"precioUnitario":59726,"subtotal":59726},{"tipo":"material","nombre":"Materiales","codigo":"Mat-001","cantidad":1.0,"precioUnitario":17255,"subtotal":17255},{"tipo":"lubricante","nombre":"Aceite de Motor Mobil Delvac 1300 Super 15W 40 (15W/40  CJ-4)","codigo":"106324","cantidad":6.3,"precioUnitario":9124,"subtotal":57479}],"totalConIva":389000,"totalNeto":326891,"conDescuento":null,"gratis":false,"operaciones":[{"nombre":"Aceite de Motor/ fIltro","accion":"C"},{"nombre":"Aceite de Transmision MT","accion":"I"},{"nombre":"Liquido de Frenos","accion":"C"},{"nombre":"Refrigerante","accion":"I"},{"nombre":"Liquido Limpia Parabrisas","accion":"I"},{"nombre":"Filtro de Aire","accion":"C"},{"nombre":"Filtro de Polen","accion":"I"},{"nombre":"Filtro de Combustible","accion":"C"},{"nombre":"PRE -Filtro de Combustible","accion":"C"},{"nombre":"Golilla tapon de carter","accion":"C"},{"nombre":"correa de accesorios","accion":"I"},{"nombre":"Aceite de direccion","accion":"I"},{"nombre":"Revision sistema de direccion","accion":"I"},{"nombre":"Reapriete tren tras/delan","accion":"I"},{"nombre":"Servicios de frenos/ freno de mano","accion":"I"},{"nombre":"Diferencial trasero","accion":"I"},{"nombre":"Diferencial delantero (4wd / T6,T8,T9)","accion":"I"},{"nombre":"Caja de transferencia  (4wd / T6,T8,T9)","accion":"I"},{"nombre":"Revisar fugas y nivel de adblue.","accion":"I"},{"nombre":"Lectura momoria de averías","accion":"I"}],"totalCalculado":388877},{"n":9,"km":90000,"etiqueta":"90.000 km","meses":54,"horas":2.0,"manoObra":89100,"items":[{"tipo":"repuesto","nombre":"Filtro de Aceite","codigo":"1010320FD060","cantidad":1.0,"precioUnitario":13752,"subtotal":13752},{"tipo":"repuesto","nombre":"Filtro de Polén","codigo":"8126108W5000","cantidad":1.0,"precioUnitario":5469,"subtotal":5469},{"tipo":"material","nombre":"Materiales","codigo":"Mat-001","cantidad":1.0,"precioUnitario":17255,"subtotal":17255},{"tipo":"lubricante","nombre":"Aceite de Motor Mobil Delvac 1300 Super 15W 40 (15W/40  CJ-4)","codigo":"106324","cantidad":6.3,"precioUnitario":9124,"subtotal":57479},{"tipo":"lubricante","nombre":"Aceite diferencial Mobilube Hd Plus 80w-90 (Gl-5)","codigo":"100214","cantidad":2.4,"precioUnitario":7186,"subtotal":17247}],"totalConIva":200000,"totalNeto":168067,"conDescuento":null,"gratis":false,"operaciones":[{"nombre":"Aceite de Motor/ fIltro","accion":"C"},{"nombre":"Aceite de Transmision MT","accion":"I"},{"nombre":"Liquido de Frenos","accion":"I"},{"nombre":"Refrigerante","accion":"I"},{"nombre":"Liquido Limpia Parabrisas","accion":"I"},{"nombre":"Filtro de Aire","accion":"I"},{"nombre":"Filtro de Polen","accion":"I"},{"nombre":"Filtro de Combustible","accion":"I"},{"nombre":"PRE -Filtro de Combustible","accion":"I"},{"nombre":"Golilla tapon de carter","accion":"C"},{"nombre":"correa de accesorios","accion":"I"},{"nombre":"Aceite de direccion","accion":"I"},{"nombre":"Revision sistema de direccion","accion":"I"},{"nombre":"Reapriete tren tras/delan","accion":"I"},{"nombre":"Servicios de frenos/ freno de mano","accion":"I"},{"nombre":"Diferencial trasero","accion":"C"},{"nombre":"Diferencial delantero (4wd / T6,T8,T9)","accion":"C"},{"nombre":"Caja de transferencia  (4wd / T6,T8,T9)","accion":"C"},{"nombre":"Revisar fugas y nivel de adblue.","accion":"I"},{"nombre":"Lectura momoria de averías","accion":"I"}],"totalCalculado":200303},{"n":10,"km":100000,"etiqueta":"100.000 km","meses":60,"horas":3.0,"manoObra":133650,"items":[{"tipo":"repuesto","nombre":"Filtro de Aceite","codigo":"1010320FD060","cantidad":1.0,"precioUnitario":13752,"subtotal":13752},{"tipo":"repuesto","nombre":"Filtro de Aire","codigo":"1109140W5000","cantidad":1.0,"precioUnitario":25014,"subtotal":25014},{"tipo":"repuesto","nombre":"Filtro  de Combustible","codigo":"1105012W5030","cantidad":1.0,"precioUnitario":59726,"subtotal":59726},{"tipo":"repuesto","nombre":"PRE-Filtro de Combustible","codigo":"1105022W5032","cantidad":1.0,"precioUnitario":59726,"subtotal":59726},{"tipo":"material","nombre":"Materiales","codigo":"Mat-001","cantidad":1.0,"precioUnitario":17255,"subtotal":17255},{"tipo":"lubricante","nombre":"Aceite de Motor Mobil Delvac 1300 Super 15W 40 (15W/40  CJ-4)","codigo":"106324","cantidad":6.3,"precioUnitario":9124,"subtotal":57479},{"tipo":"lubricante","nombre":"Aceite de transmision Mobilube 1 Shc 75w-90 GL-4","codigo":"100219","cantidad":2.4,"precioUnitario":31458,"subtotal":75498},{"tipo":"lubricante","nombre":"Aceite de Dirección","codigo":"100280","cantidad":1.7,"precioUnitario":8180,"subtotal":13906},{"tipo":"lubricante","nombre":"Anticongelante Mobil Super ELC 50%","codigo":"105892","cantidad":11.5,"precioUnitario":7765,"subtotal":89295}],"totalConIva":545000,"totalNeto":457983,"conDescuento":null,"gratis":false,"operaciones":[{"nombre":"Aceite de Motor/ fIltro","accion":"C"},{"nombre":"Aceite de Transmision MT","accion":"C"},{"nombre":"Liquido de Frenos","accion":"I"},{"nombre":"Refrigerante","accion":"C"},{"nombre":"Liquido Limpia Parabrisas","accion":"I"},{"nombre":"Filtro de Aire","accion":"C"},{"nombre":"Filtro de Polen","accion":"I"},{"nombre":"Filtro de Combustible","accion":"C"},{"nombre":"PRE -Filtro de Combustible","accion":"C"},{"nombre":"Golilla tapon de carter","accion":"C"},{"nombre":"correa de accesorios","accion":"I"},{"nombre":"Aceite de direccion","accion":"C"},{"nombre":"Revision sistema de direccion","accion":"I"},{"nombre":"Reapriete tren tras/delan","accion":"I"},{"nombre":"Servicios de frenos/ freno de mano","accion":"I"},{"nombre":"Diferencial trasero","accion":"I"},{"nombre":"Diferencial delantero (4wd / T6,T8,T9)","accion":"I"},{"nombre":"Caja de transferencia  (4wd / T6,T8,T9)","accion":"I"},{"nombre":"Revisar fugas y nivel de adblue.","accion":"I"},{"nombre":"Lectura momoria de averías","accion":"I"}],"totalCalculado":545301}]}],"adicionales":[{"nombre":"Alineación y balanceo","precio":35640,"porKm":{"20000":35640,"40000":35640,"60000":35640,"80000":35640,"100000":35640}}],"packs":[],"notas":["El valor de las mantenciones es un valor referencial sugerido; confírmalo con tu concesionario Curifor.","En el costo de las mantenciones no se incluyen reparaciones ni piezas de desgaste (pastillas de freno, neumáticos, plumillas, etc.).","Se recomienda su realización según kilometraje o tiempo, lo que ocurra primero."],"fuente":"Pauta de mantencion JAC Enero 2026.xlsx / hoja 'X200 E5'"}